convcom/__init__.py
convcom/v1/__init__.py
convcom/v1/exceptions.py
convcom/v1/parse.py
convcom/v1/types.py
convcom/v1/unparse.py
convcom-0.1.2.dist-info/LICENSE.md
convcom-0.1.2.dist-info/METADATA
convcom-0.1.2.dist-info/WHEEL
convcom-0.1.2.dist-info/top_level.txt
convcom-0.1.2.dist-info/RECORD
