Metadata-Version: 2.1
Name: convcom
Version: 0.1.2
Summary: A simple pure-Python module for parsing conventional commits.
Author-email: Alex Weatherhead <22604743+Alex-Weatherhead@users.noreply.github.com>
Maintainer-email: Alex Weatherhead <22604743+Alex-Weatherhead@users.noreply.github.com>
License: 
Project-URL: Repository, https://github.com/Alex-Weatherhead/convcom
Project-URL: Issues, https://github.com/Alex-Weatherhead/convcom/issues
Keywords: Conventional Commits
Classifier: Development Status :: 4 - Beta
Classifier: Programming Language :: Python
Requires-Python: >=3.8
License-File: LICENSE.md
Provides-Extra: development
Requires-Dist: black >=24.4.0 ; extra == 'development'
Requires-Dist: mypy >=1.9.0 ; extra == 'development'
Requires-Dist: pytest >=7.4.1 ; extra == 'development'
Requires-Dist: twine >=5.0.0 ; extra == 'development'
